LICENSE
MANIFEST.in
README.md
setup.cfg
setup.py
Django_Gtranslate.egg-info/PKG-INFO
Django_Gtranslate.egg-info/SOURCES.txt
Django_Gtranslate.egg-info/dependency_links.txt
Django_Gtranslate.egg-info/requires.txt
Django_Gtranslate.egg-info/top_level.txt
gtranslate/__init__.py
gtranslate/models.py
gtranslate/tests.py
gtranslate/urls.py
gtranslate/urls_auth.py
gtranslate/views.py
gtranslate/templatetags/__init__.py
gtranslate/templatetags/gtranslate.py